recode_geohash/__init__.py
recode_geohash/core.py
recode_geohash-0.1.0.dist-info/licenses/LICENSE
recode_geohash-0.1.0.dist-info/METADATA
recode_geohash-0.1.0.dist-info/WHEEL
recode_geohash-0.1.0.dist-info/top_level.txt
recode_geohash-0.1.0.dist-info/RECORD
